{
  "@context": "http://iiif.io/api/presentation/2/context.json",
  "@id": "https://iiif.ghentcdh.ugent.be/iiif/manifests/primitief_kadaster:550_0001_000_06766_000",
  "@type": "sc:Manifest",
  "label": "Waasmunster - Sectie B",
  "metadata": [
    {
      "label": "Provincie",
      "value": "OOST-VLAANDEREN"
    },
    {
      "label": "Fusiegemeente",
      "value": "WAASMUNSTER"
    },
    {
      "label": "Deelgemeente",
      "value": "Waasmunster"
    },
    {
      "label": "Lengteg",
      "value": "4.08573"
    },
    {
      "label": "Breedteg",
      "value": "51.10572"
    },
    {
      "label": "Sectie",
      "value": "Sectie B"
    },
    {
      "label": "Periode",
      "value": "[1830-1833]"
    },
    {
      "label": "Opmerkingen",
      "value": "Naam landmeter = Delhaije"
    }
  ],
  "thumbnail": {
    "@id": "https://iiif.ghentcdh.ugent.be/iiif/images/primitief_kadaster:550_0001_000_06766_000:550_0001_000_06766_000_0_0001/full/!80,100/0/default.jpg",
    "service": {
      "@context": "http://iiif.io/api/image/2/context.json",
      "@id": "https://iiif.ghentcdh.ugent.be/iiif/images/primitief_kadaster:550_0001_000_06766_000:550_0001_000_06766_000_0_0001",
      "profile": "http://iiif.io/api/image/2/level1.json"
    },
    "@type": "dctypes:Image"
  },
  "sequences": [
    {
      "@id": "https://iiif.ghentcdh.ugent.be/iiif/manifests/primitief_kadaster:550_0001_000_06766_000/sequence/default",
      "@type": "sc:Sequence",
      "label": "Default",
      "canvases": [
        {
          "@id": "https://iiif.ghentcdh.ugent.be/iiif/manifests/primitief_kadaster:550_0001_000_06766_000/canvas/550_0001_000_06766_000_0_0001",
          "@type": "sc:Canvas",
          "height": 11116,
          "width": 7016,
          "label": "Waasmunster - Sectie B, Percelen van 1 tot 49, 'Het Oosten'",
          "metadata": [],
          "images": [
            {
              "@id": "https://iiif.ghentcdh.ugent.be/iiif/manifests/primitief_kadaster:550_0001_000_06766_000/annotation/550_0001_000_06766_000_0_0001",
              "@type": "oa:Annotation",
              "motivation": "sc:painting",
              "on": "https://iiif.ghentcdh.ugent.be/iiif/manifests/primitief_kadaster:550_0001_000_06766_000/canvas/550_0001_000_06766_000_0_0001",
              "resource": {
                "@id": "https://iiif.ghentcdh.ugent.be/iiif/images/primitief_kadaster:550_0001_000_06766_000:550_0001_000_06766_000_0_0001/full/full/0/default.jpg",
                "@type": "dctypes:Image",
                "format": "image/jpeg",
                "height": 11116,
                "width": 7016,
                "service": {
                  "@context": "http://iiif.io/api/image/2/context.json",
                  "@id": "https://iiif.ghentcdh.ugent.be/iiif/images/primitief_kadaster:550_0001_000_06766_000:550_0001_000_06766_000_0_0001",
                  "profile": "http://iiif.io/api/image/2/level1.json"
                }
              }
            }
          ]
        },
        {
          "@id": "https://iiif.ghentcdh.ugent.be/iiif/manifests/primitief_kadaster:550_0001_000_06766_000/canvas/550_0001_000_06766_000_0_0002",
          "@type": "sc:Canvas",
          "height": 11480,
          "width": 7676,
          "label": "Waasmunster - Sectie B, Percelen van 50 tot 389, 'Het Oosten'",
          "metadata": [],
          "images": [
            {
              "@id": "https://iiif.ghentcdh.ugent.be/iiif/manifests/primitief_kadaster:550_0001_000_06766_000/annotation/550_0001_000_06766_000_0_0002",
              "@type": "oa:Annotation",
              "motivation": "sc:painting",
              "on": "https://iiif.ghentcdh.ugent.be/iiif/manifests/primitief_kadaster:550_0001_000_06766_000/canvas/550_0001_000_06766_000_0_0002",
              "resource": {
                "@id": "https://iiif.ghentcdh.ugent.be/iiif/images/primitief_kadaster:550_0001_000_06766_000:550_0001_000_06766_000_0_0002/full/full/0/default.jpg",
                "@type": "dctypes:Image",
                "format": "image/jpeg",
                "height": 11480,
                "width": 7676,
                "service": {
                  "@context": "http://iiif.io/api/image/2/context.json",
                  "@id": "https://iiif.ghentcdh.ugent.be/iiif/images/primitief_kadaster:550_0001_000_06766_000:550_0001_000_06766_000_0_0002",
                  "profile": "http://iiif.io/api/image/2/level1.json"
                }
              }
            }
          ]
        },
        {
          "@id": "https://iiif.ghentcdh.ugent.be/iiif/manifests/primitief_kadaster:550_0001_000_06766_000/canvas/550_0001_000_06766_000_0_0003",
          "@type": "sc:Canvas",
          "height": 11719,
          "width": 7916,
          "label": "Waasmunster - Sectie B, Percelen van 390 tot 720, 'Het Oosten'",
          "metadata": [],
          "images": [
            {
              "@id": "https://iiif.ghentcdh.ugent.be/iiif/manifests/primitief_kadaster:550_0001_000_06766_000/annotation/550_0001_000_06766_000_0_0003",
              "@type": "oa:Annotation",
              "motivation": "sc:painting",
              "on": "https://iiif.ghentcdh.ugent.be/iiif/manifests/primitief_kadaster:550_0001_000_06766_000/canvas/550_0001_000_06766_000_0_0003",
              "resource": {
                "@id": "https://iiif.ghentcdh.ugent.be/iiif/images/primitief_kadaster:550_0001_000_06766_000:550_0001_000_06766_000_0_0003/full/full/0/default.jpg",
                "@type": "dctypes:Image",
                "format": "image/jpeg",
                "height": 11719,
                "width": 7916,
                "service": {
                  "@context": "http://iiif.io/api/image/2/context.json",
                  "@id": "https://iiif.ghentcdh.ugent.be/iiif/images/primitief_kadaster:550_0001_000_06766_000:550_0001_000_06766_000_0_0003",
                  "profile": "http://iiif.io/api/image/2/level1.json"
                }
              }
            }
          ]
        },
        {
          "@id": "https://iiif.ghentcdh.ugent.be/iiif/manifests/primitief_kadaster:550_0001_000_06766_000/canvas/550_0001_000_06766_000_0_0004",
          "@type": "sc:Canvas",
          "height": 7816,
          "width": 11577,
          "label": "Waasmunster - Sectie B, Percelen van 721 tot 961, 'Het Oosten'",
          "metadata": [],
          "images": [
            {
              "@id": "https://iiif.ghentcdh.ugent.be/iiif/manifests/primitief_kadaster:550_0001_000_06766_000/annotation/550_0001_000_06766_000_0_0004",
              "@type": "oa:Annotation",
              "motivation": "sc:painting",
              "on": "https://iiif.ghentcdh.ugent.be/iiif/manifests/primitief_kadaster:550_0001_000_06766_000/canvas/550_0001_000_06766_000_0_0004",
              "resource": {
                "@id": "https://iiif.ghentcdh.ugent.be/iiif/images/primitief_kadaster:550_0001_000_06766_000:550_0001_000_06766_000_0_0004/full/full/0/default.jpg",
                "@type": "dctypes:Image",
                "format": "image/jpeg",
                "height": 7816,
                "width": 11577,
                "service": {
                  "@context": "http://iiif.io/api/image/2/context.json",
                  "@id": "https://iiif.ghentcdh.ugent.be/iiif/images/primitief_kadaster:550_0001_000_06766_000:550_0001_000_06766_000_0_0004",
                  "profile": "http://iiif.io/api/image/2/level1.json"
                }
              }
            }
          ]
        },
        {
          "@id": "https://iiif.ghentcdh.ugent.be/iiif/manifests/primitief_kadaster:550_0001_000_06766_000/canvas/550_0001_000_06766_000_0_0005",
          "@type": "sc:Canvas",
          "height": 7816,
          "width": 11804,
          "label": "Waasmunster - Sectie B, Percelen van 962 tot 1270, 'Het Oosten'",
          "metadata": [],
          "images": [
            {
              "@id": "https://iiif.ghentcdh.ugent.be/iiif/manifests/primitief_kadaster:550_0001_000_06766_000/annotation/550_0001_000_06766_000_0_0005",
              "@type": "oa:Annotation",
              "motivation": "sc:painting",
              "on": "https://iiif.ghentcdh.ugent.be/iiif/manifests/primitief_kadaster:550_0001_000_06766_000/canvas/550_0001_000_06766_000_0_0005",
              "resource": {
                "@id": "https://iiif.ghentcdh.ugent.be/iiif/images/primitief_kadaster:550_0001_000_06766_000:550_0001_000_06766_000_0_0005/full/full/0/default.jpg",
                "@type": "dctypes:Image",
                "format": "image/jpeg",
                "height": 7816,
                "width": 11804,
                "service": {
                  "@context": "http://iiif.io/api/image/2/context.json",
                  "@id": "https://iiif.ghentcdh.ugent.be/iiif/images/primitief_kadaster:550_0001_000_06766_000:550_0001_000_06766_000_0_0005",
                  "profile": "http://iiif.io/api/image/2/level1.json"
                }
              }
            }
          ]
        },
        {
          "@id": "https://iiif.ghentcdh.ugent.be/iiif/manifests/primitief_kadaster:550_0001_000_06766_000/canvas/550_0001_000_06766_000_0_0006",
          "@type": "sc:Canvas",
          "height": 11368,
          "width": 7844,
          "label": "Waasmunster - Sectie B, Percelen van 1271 tot 1373, 'Het Oosten'",
          "metadata": [],
          "images": [
            {
              "@id": "https://iiif.ghentcdh.ugent.be/iiif/manifests/primitief_kadaster:550_0001_000_06766_000/annotation/550_0001_000_06766_000_0_0006",
              "@type": "oa:Annotation",
              "motivation": "sc:painting",
              "on": "https://iiif.ghentcdh.ugent.be/iiif/manifests/primitief_kadaster:550_0001_000_06766_000/canvas/550_0001_000_06766_000_0_0006",
              "resource": {
                "@id": "https://iiif.ghentcdh.ugent.be/iiif/images/primitief_kadaster:550_0001_000_06766_000:550_0001_000_06766_000_0_0006/full/full/0/default.jpg",
                "@type": "dctypes:Image",
                "format": "image/jpeg",
                "height": 11368,
                "width": 7844,
                "service": {
                  "@context": "http://iiif.io/api/image/2/context.json",
                  "@id": "https://iiif.ghentcdh.ugent.be/iiif/images/primitief_kadaster:550_0001_000_06766_000:550_0001_000_06766_000_0_0006",
                  "profile": "http://iiif.io/api/image/2/level1.json"
                }
              }
            }
          ]
        },
        {
          "@id": "https://iiif.ghentcdh.ugent.be/iiif/manifests/primitief_kadaster:550_0001_000_06766_000/canvas/550_0001_000_06766_000_0_0007",
          "@type": "sc:Canvas",
          "height": 11743,
          "width": 7756,
          "label": "Waasmunster - Sectie B, Percelen van 1375 tot 1867, 'Het Oosten'",
          "metadata": [],
          "images": [
            {
              "@id": "https://iiif.ghentcdh.ugent.be/iiif/manifests/primitief_kadaster:550_0001_000_06766_000/annotation/550_0001_000_06766_000_0_0007",
              "@type": "oa:Annotation",
              "motivation": "sc:painting",
              "on": "https://iiif.ghentcdh.ugent.be/iiif/manifests/primitief_kadaster:550_0001_000_06766_000/canvas/550_0001_000_06766_000_0_0007",
              "resource": {
                "@id": "https://iiif.ghentcdh.ugent.be/iiif/images/primitief_kadaster:550_0001_000_06766_000:550_0001_000_06766_000_0_0007/full/full/0/default.jpg",
                "@type": "dctypes:Image",
                "format": "image/jpeg",
                "height": 11743,
                "width": 7756,
                "service": {
                  "@context": "http://iiif.io/api/image/2/context.json",
                  "@id": "https://iiif.ghentcdh.ugent.be/iiif/images/primitief_kadaster:550_0001_000_06766_000:550_0001_000_06766_000_0_0007",
                  "profile": "http://iiif.io/api/image/2/level1.json"
                }
              }
            }
          ]
        },
        {
          "@id": "https://iiif.ghentcdh.ugent.be/iiif/manifests/primitief_kadaster:550_0001_000_06766_000/canvas/550_0001_000_06766_000_0_0008",
          "@type": "sc:Canvas",
          "height": 10480,
          "width": 7504,
          "label": "Waasmunster - Sectie B, Percelen van 1868 tot 2215, 'Het Oosten'",
          "metadata": [],
          "images": [
            {
              "@id": "https://iiif.ghentcdh.ugent.be/iiif/manifests/primitief_kadaster:550_0001_000_06766_000/annotation/550_0001_000_06766_000_0_0008",
              "@type": "oa:Annotation",
              "motivation": "sc:painting",
              "on": "https://iiif.ghentcdh.ugent.be/iiif/manifests/primitief_kadaster:550_0001_000_06766_000/canvas/550_0001_000_06766_000_0_0008",
              "resource": {
                "@id": "https://iiif.ghentcdh.ugent.be/iiif/images/primitief_kadaster:550_0001_000_06766_000:550_0001_000_06766_000_0_0008/full/full/0/default.jpg",
                "@type": "dctypes:Image",
                "format": "image/jpeg",
                "height": 10480,
                "width": 7504,
                "service": {
                  "@context": "http://iiif.io/api/image/2/context.json",
                  "@id": "https://iiif.ghentcdh.ugent.be/iiif/images/primitief_kadaster:550_0001_000_06766_000:550_0001_000_06766_000_0_0008",
                  "profile": "http://iiif.io/api/image/2/level1.json"
                }
              }
            }
          ]
        }
      ]
    }
  ]
}