{
  "@context": "http://iiif.io/api/presentation/2/context.json",
  "@id": "https://iiif.ghentcdh.ugent.be/iiif/manifests/primitief_kadaster:550_0001_000_06002_000",
  "@type": "sc:Manifest",
  "label": "Buggenhout - Sectie C",
  "metadata": [
    {
      "label": "Provincie",
      "value": "OOST-VLAANDEREN"
    },
    {
      "label": "Fusiegemeente",
      "value": "BUGGENHOUT"
    },
    {
      "label": "Deelgemeente",
      "value": "Buggenhout"
    },
    {
      "label": "Lengteg",
      "value": "4.20173"
    },
    {
      "label": "Breedteg",
      "value": "51.0159"
    },
    {
      "label": "Sectie",
      "value": "Sectie C"
    },
    {
      "label": "Periode",
      "value": "[1830-1833]"
    },
    {
      "label": "Artemis pipeline",
      "value": "Compiled manifest with mirrored Allmaps georeferencing (manifest- and canvas-level)"
    }
  ],
  "thumbnail": {
    "@id": "https://iiif.ghentcdh.ugent.be/iiif/images/primitief_kadaster:550_0001_000_06002_000:550_0001_000_06002_000_0_0001/full/!80,100/0/default.jpg",
    "service": {
      "@context": "http://iiif.io/api/image/2/context.json",
      "@id": "https://iiif.ghentcdh.ugent.be/iiif/images/primitief_kadaster:550_0001_000_06002_000:550_0001_000_06002_000_0_0001",
      "profile": "http://iiif.io/api/image/2/level1.json"
    },
    "@type": "dctypes:Image"
  },
  "sequences": [
    {
      "@id": "https://iiif.ghentcdh.ugent.be/iiif/manifests/primitief_kadaster:550_0001_000_06002_000/sequence/default",
      "@type": "sc:Sequence",
      "label": "Default",
      "canvases": [
        {
          "@id": "https://iiif.ghentcdh.ugent.be/iiif/manifests/primitief_kadaster:550_0001_000_06002_000/canvas/550_0001_000_06002_000_0_0001",
          "@type": "sc:Canvas",
          "height": 7536,
          "width": 11558,
          "label": "Buggenhout - Sectie C, Percelen van 1 tot 97",
          "metadata": [],
          "images": [
            {
              "@id": "https://iiif.ghentcdh.ugent.be/iiif/manifests/primitief_kadaster:550_0001_000_06002_000/annotation/550_0001_000_06002_000_0_0001",
              "@type": "oa:Annotation",
              "motivation": "sc:painting",
              "on": "https://iiif.ghentcdh.ugent.be/iiif/manifests/primitief_kadaster:550_0001_000_06002_000/canvas/550_0001_000_06002_000_0_0001",
              "resource": {
                "@id": "https://iiif.ghentcdh.ugent.be/iiif/images/primitief_kadaster:550_0001_000_06002_000:550_0001_000_06002_000_0_0001/full/full/0/default.jpg",
                "@type": "dctypes:Image",
                "format": "image/jpeg",
                "height": 7536,
                "width": 11558,
                "service": {
                  "@context": "http://iiif.io/api/image/2/context.json",
                  "@id": "https://iiif.ghentcdh.ugent.be/iiif/images/primitief_kadaster:550_0001_000_06002_000:550_0001_000_06002_000_0_0001",
                  "profile": "http://iiif.io/api/image/2/level1.json"
                }
              }
            }
          ],
          "otherContent": [
            {
              "@id": "allmaps/canvases/7bc3c417c9155ddb.json",
              "@type": "sc:AnnotationList",
              "label": "Georeferencing (Allmaps, mirrored by Artemis)"
            }
          ]
        },
        {
          "@id": "https://iiif.ghentcdh.ugent.be/iiif/manifests/primitief_kadaster:550_0001_000_06002_000/canvas/550_0001_000_06002_000_0_0002",
          "@type": "sc:Canvas",
          "height": 8068,
          "width": 11447,
          "label": "Buggenhout - Sectie C, Percelen van 98 tot 717",
          "metadata": [],
          "images": [
            {
              "@id": "https://iiif.ghentcdh.ugent.be/iiif/manifests/primitief_kadaster:550_0001_000_06002_000/annotation/550_0001_000_06002_000_0_0002",
              "@type": "oa:Annotation",
              "motivation": "sc:painting",
              "on": "https://iiif.ghentcdh.ugent.be/iiif/manifests/primitief_kadaster:550_0001_000_06002_000/canvas/550_0001_000_06002_000_0_0002",
              "resource": {
                "@id": "https://iiif.ghentcdh.ugent.be/iiif/images/primitief_kadaster:550_0001_000_06002_000:550_0001_000_06002_000_0_0002/full/full/0/default.jpg",
                "@type": "dctypes:Image",
                "format": "image/jpeg",
                "height": 8068,
                "width": 11447,
                "service": {
                  "@context": "http://iiif.io/api/image/2/context.json",
                  "@id": "https://iiif.ghentcdh.ugent.be/iiif/images/primitief_kadaster:550_0001_000_06002_000:550_0001_000_06002_000_0_0002",
                  "profile": "http://iiif.io/api/image/2/level1.json"
                }
              }
            }
          ],
          "otherContent": [
            {
              "@id": "allmaps/canvases/0ae1c44d9386296c.json",
              "@type": "sc:AnnotationList",
              "label": "Georeferencing (Allmaps, mirrored by Artemis)"
            }
          ]
        }
      ]
    }
  ]
}