{
  "@context": "http://iiif.io/api/presentation/2/context.json",
  "@id": "https://iiif.ghentcdh.ugent.be/iiif/manifests/primitief_kadaster:550_0001_000_06225_000",
  "@type": "sc:Manifest",
  "label": "Drongen - Sectie C",
  "metadata": [
    {
      "label": "Provincie",
      "value": "OOST-VLAANDEREN"
    },
    {
      "label": "Fusiegemeente",
      "value": "GENT"
    },
    {
      "label": "Deelgemeente",
      "value": "Drongen"
    },
    {
      "label": "Lengteg",
      "value": "3.65649"
    },
    {
      "label": "Breedteg",
      "value": "51.05067"
    },
    {
      "label": "Sectie",
      "value": "Sectie C"
    },
    {
      "label": "Periode",
      "value": "[1830-1833]"
    },
    {
      "label": "Opmerkingen",
      "value": "Naam landmeter = De Scrobeliere"
    }
  ],
  "thumbnail": {
    "@id": "https://iiif.ghentcdh.ugent.be/iiif/images/primitief_kadaster:550_0001_000_06225_000:550_0001_000_06225_000_0_0001/full/!80,100/0/default.jpg",
    "service": {
      "@context": "http://iiif.io/api/image/2/context.json",
      "@id": "https://iiif.ghentcdh.ugent.be/iiif/images/primitief_kadaster:550_0001_000_06225_000:550_0001_000_06225_000_0_0001",
      "profile": "http://iiif.io/api/image/2/level1.json"
    },
    "@type": "dctypes:Image"
  },
  "sequences": [
    {
      "@id": "https://iiif.ghentcdh.ugent.be/iiif/manifests/primitief_kadaster:550_0001_000_06225_000/sequence/default",
      "@type": "sc:Sequence",
      "label": "Default",
      "canvases": [
        {
          "@id": "https://iiif.ghentcdh.ugent.be/iiif/manifests/primitief_kadaster:550_0001_000_06225_000/canvas/550_0001_000_06225_000_0_0001",
          "@type": "sc:Canvas",
          "height": 7720,
          "width": 10936,
          "label": "Drongen - Sectie C, Percelen van 1 tot 382, 'het Zuiden'",
          "metadata": [],
          "images": [
            {
              "@id": "https://iiif.ghentcdh.ugent.be/iiif/manifests/primitief_kadaster:550_0001_000_06225_000/annotation/550_0001_000_06225_000_0_0001",
              "@type": "oa:Annotation",
              "motivation": "sc:painting",
              "on": "https://iiif.ghentcdh.ugent.be/iiif/manifests/primitief_kadaster:550_0001_000_06225_000/canvas/550_0001_000_06225_000_0_0001",
              "resource": {
                "@id": "https://iiif.ghentcdh.ugent.be/iiif/images/primitief_kadaster:550_0001_000_06225_000:550_0001_000_06225_000_0_0001/full/full/0/default.jpg",
                "@type": "dctypes:Image",
                "format": "image/jpeg",
                "height": 7720,
                "width": 10936,
                "service": {
                  "@context": "http://iiif.io/api/image/2/context.json",
                  "@id": "https://iiif.ghentcdh.ugent.be/iiif/images/primitief_kadaster:550_0001_000_06225_000:550_0001_000_06225_000_0_0001",
                  "profile": "http://iiif.io/api/image/2/level1.json"
                }
              }
            }
          ]
        },
        {
          "@id": "https://iiif.ghentcdh.ugent.be/iiif/manifests/primitief_kadaster:550_0001_000_06225_000/canvas/550_0001_000_06225_000_0_0002",
          "@type": "sc:Canvas",
          "height": 7840,
          "width": 11846,
          "label": "Drongen - Sectie C, Percelen van 383 tot 828, 'het Zuiden'",
          "metadata": [],
          "images": [
            {
              "@id": "https://iiif.ghentcdh.ugent.be/iiif/manifests/primitief_kadaster:550_0001_000_06225_000/annotation/550_0001_000_06225_000_0_0002",
              "@type": "oa:Annotation",
              "motivation": "sc:painting",
              "on": "https://iiif.ghentcdh.ugent.be/iiif/manifests/primitief_kadaster:550_0001_000_06225_000/canvas/550_0001_000_06225_000_0_0002",
              "resource": {
                "@id": "https://iiif.ghentcdh.ugent.be/iiif/images/primitief_kadaster:550_0001_000_06225_000:550_0001_000_06225_000_0_0002/full/full/0/default.jpg",
                "@type": "dctypes:Image",
                "format": "image/jpeg",
                "height": 7840,
                "width": 11846,
                "service": {
                  "@context": "http://iiif.io/api/image/2/context.json",
                  "@id": "https://iiif.ghentcdh.ugent.be/iiif/images/primitief_kadaster:550_0001_000_06225_000:550_0001_000_06225_000_0_0002",
                  "profile": "http://iiif.io/api/image/2/level1.json"
                }
              }
            }
          ]
        },
        {
          "@id": "https://iiif.ghentcdh.ugent.be/iiif/manifests/primitief_kadaster:550_0001_000_06225_000/canvas/550_0001_000_06225_000_0_0003",
          "@type": "sc:Canvas",
          "height": 7868,
          "width": 11840,
          "label": "Drongen - Sectie C, Percelen van 829 tot 1180, 'het Zuiden'",
          "metadata": [],
          "images": [
            {
              "@id": "https://iiif.ghentcdh.ugent.be/iiif/manifests/primitief_kadaster:550_0001_000_06225_000/annotation/550_0001_000_06225_000_0_0003",
              "@type": "oa:Annotation",
              "motivation": "sc:painting",
              "on": "https://iiif.ghentcdh.ugent.be/iiif/manifests/primitief_kadaster:550_0001_000_06225_000/canvas/550_0001_000_06225_000_0_0003",
              "resource": {
                "@id": "https://iiif.ghentcdh.ugent.be/iiif/images/primitief_kadaster:550_0001_000_06225_000:550_0001_000_06225_000_0_0003/full/full/0/default.jpg",
                "@type": "dctypes:Image",
                "format": "image/jpeg",
                "height": 7868,
                "width": 11840,
                "service": {
                  "@context": "http://iiif.io/api/image/2/context.json",
                  "@id": "https://iiif.ghentcdh.ugent.be/iiif/images/primitief_kadaster:550_0001_000_06225_000:550_0001_000_06225_000_0_0003",
                  "profile": "http://iiif.io/api/image/2/level1.json"
                }
              }
            }
          ]
        },
        {
          "@id": "https://iiif.ghentcdh.ugent.be/iiif/manifests/primitief_kadaster:550_0001_000_06225_000/canvas/550_0001_000_06225_000_0_0004",
          "@type": "sc:Canvas",
          "height": 7836,
          "width": 11812,
          "label": "Drongen - Sectie C, Percelen van 1181 tot 1390, 'het Zuiden'",
          "metadata": [],
          "images": [
            {
              "@id": "https://iiif.ghentcdh.ugent.be/iiif/manifests/primitief_kadaster:550_0001_000_06225_000/annotation/550_0001_000_06225_000_0_0004",
              "@type": "oa:Annotation",
              "motivation": "sc:painting",
              "on": "https://iiif.ghentcdh.ugent.be/iiif/manifests/primitief_kadaster:550_0001_000_06225_000/canvas/550_0001_000_06225_000_0_0004",
              "resource": {
                "@id": "https://iiif.ghentcdh.ugent.be/iiif/images/primitief_kadaster:550_0001_000_06225_000:550_0001_000_06225_000_0_0004/full/full/0/default.jpg",
                "@type": "dctypes:Image",
                "format": "image/jpeg",
                "height": 7836,
                "width": 11812,
                "service": {
                  "@context": "http://iiif.io/api/image/2/context.json",
                  "@id": "https://iiif.ghentcdh.ugent.be/iiif/images/primitief_kadaster:550_0001_000_06225_000:550_0001_000_06225_000_0_0004",
                  "profile": "http://iiif.io/api/image/2/level1.json"
                }
              }
            }
          ]
        }
      ]
    }
  ]
}